ejercicio5/ejercicio5.v
// GATE LEVEL MODEL EJECICIO 5

// ECUACION SOP

module gateLevel1(input wire A, B, C, output wire Y);

  wire notA, notC, notB, w1, w2, w3;

  not (notA, A);
  not (notB, B);
  not (notC, C);
  and (w1, A, notB , notC);
  and (w2, A, notB, C);
  and (w3, A, B, C);
  or  (Y, w1, w2, w3);

endmodule

// ECUACION POS

module gateLevel2(input wire A, B, C, output wire Y);

  wire notA, notC, notB, w1, w2, w3, w4, w5;

  not (notA, A);
  not (notB, B);
  not (notC, C);
  or (w1, A, B , C);
  or (w2, A, B, notC);
  or (w3, A, notB, C);
  or (w4, A, notB, notC);
  or (w5, notA, notB, C);
  and (Y, w1, w2, w3, w4, w5);

endmodule


// ECUACION MINIMIZADA Y = ( AB' + AC )

module gateLevel3(input wire A, B, C, output wire Y);

  wire notA, notC, notB, w1, w2;

  not (notA, A);
  not (notB, B);
  not (notC, C);
  and (w1, A, notB);
  and (w2, A, C);
  or  (Y, w1, w2);

endmodule


// BEHAVIORAL MODELING EJERCICIO 5

// ECUACION SOP

module operadores1(input wire A, B, C, output wire Y);

  assign Y = (A & ~B & ~C) | (A & ~B & C) | (A & B & C);

endmodule

// ECUACION POS

module operadores2(input wire A, B, C, output wire Y);

  assign Y = (A | B | C) & (A | B | ~C) & (A | ~B | C) & (A | ~B | ~C) & (~A | ~B | C);

endmodule


// ECUACION MINIMIZADA Y = ( AB' + AC )

module operadores3(input wire A, B, C, output wire Y);

  assign Y = (A & ~B) | (A & C);

endmodule

ejercicio5/ejercicio5_tb.v
module testbench();

reg r1, r2, r3, r4, r5, r6, r7, r8, r9, r10, r11, r12, r13, r14, r15, r16, r17, r18;
wire out1, out2, out3, out4, out5, out6;

gateLevel1 G1(r1, r2, r3, out1);
gateLevel2 G2(r4, r5, r6, out2);
gateLevel3 G3(r7, r8, r9, out3);
operadores1 OP1(r10, r11, r12, out4);
operadores2 OP2(r13, r14, r15, out5);
operadores3 OP3(r16, r17, r18, out6);

initial begin
  $display(" ejercicio 5 - sistema de alarmas");
  $display("A B C | Y");
  $display("------|---");
  $monitor("%b %b %b | %b ", r1, r2, r3, out1);
  r1 = 0; r2 = 0; r3 = 0;
  #1 r3 = 1;
  #1 r2 = 1; r3 = 0;
  #1 r3 = 1;
  #1 r1 = 1; r2 = 0; r3 = 0;
  #1 r3 = 1;
  #1 r2 = 1; r3 = 0;
  #1 r3 = 1;
end

initial begin
  #10
  $display("\n");
  $display("A B C | Y");
  $display("------|---");
  $monitor("%b %b %b | %b ", r4, r5, r6, out2);
  r4 = 0; r5 = 0; r6 = 0;
  #1 r6 = 1;
  #1 r5 = 1; r6 = 0;
  #1 r6 = 1;
  #1 r4 = 1; r5 = 0; r6 = 0;
  #1 r6 = 1;
  #1 r5 = 1; r6 = 0;
  #1 r6 = 1;
end


initial begin
  #28
  $display("\n");
  $display("A B C | Y");
  $display("------|---");
  $monitor("%b %b %b | %b ", r7, r8, r9, out3);
  r7 = 0; r8 = 0; r9 = 0;
  #1 r9 = 1;
  #1 r8 = 1; r9 = 0;
  #1 r9 = 1;
  #1 r7 = 1; r8 = 0; r9 = 0;
  #1 r9 = 1;
  #1 r8 = 1; r9 = 0;
  #1 r9 = 1;
end

initial begin
  #37
  $display("\n");
  $display("A B C | Y");
  $display("------|---");
  $monitor("%b %b %b | %b ", r10, r11, r12, out4);
  r10 = 0; r11 = 0; r12 = 0;
  #1 r12 = 1;
  #1 r11 = 1; r12 = 0;
  #1 r12 = 1;
  #1 r10 = 1; r11 = 0; r12 = 0;
  #1 r12 = 1;
  #1 r11 = 1; r12 = 0;
  #1 r12 = 1;
end


initial begin
  #46
  $display("\n");
  $display("A B C | Y");
  $display("------|---");
  $monitor("%b %b %b | %b ", r13, r14, r15, out5);
  r13 = 0; r14 = 0; r15 = 0;
  #1 r15 = 1;
  #1 r14 = 1; r15 = 0;
  #1 r15 = 1;
  #1 r13 = 1; r14 = 0; r15 = 0;
  #1 r15 = 1;
  #1 r14 = 1; r15 = 0;
  #1 r15 = 1;
end

initial begin
  #55
  $display("\n");
  $display("A B C | Y");
  $display("------|---");
  $monitor("%b %b %b | %b ", r16, r17, r18, out6);
  r16 = 0; r17 = 0; r18 = 0;
  #1 r18 = 1;
  #1 r17 = 1; r18 = 0;
  #1 r18 = 1;
  #1 r16 = 1; r17 = 0; r18 = 0;
  #1 r18 = 1;
  #1 r17 = 1; r18 = 0;
  #1 r18 = 1;
end


initial
  #64 $finish;

initial begin
  $dumpfile("ejercicio5_tb.vcd");
  $dumpvars(0, testbench);
end

endmodule

ejercicio5/ejercicio5_tb.vcd
$date
	Sun Aug 09 09:27:58 2020
$end
$version
	Icarus Verilog
$end
$timescale
	1ps
$end
$scope module testbench $end
$var wire 1 ! out6 $end
$var wire 1 " out5 $end
$var wire 1 # out4 $end
$var wire 1 $ out3 $end
$var wire 1 % out2 $end
$var wire 1 & out1 $end
$var reg 1 ' r1 $end
$var reg 1 ( r10 $end
$var reg 1 ) r11 $end
$var reg 1 * r12 $end
$var reg 1 + r13 $end
$var reg 1 , r14 $end
$var reg 1 - r15 $end
$var reg 1 . r16 $end
$var reg 1 / r17 $end
$var reg 1 0 r18 $end
$var reg 1 1 r2 $end
$var reg 1 2 r3 $end
$var reg 1 3 r4 $end
$var reg 1 4 r5 $end
$var reg 1 5 r6 $end
$var reg 1 6 r7 $end
$var reg 1 7 r8 $end
$var reg 1 8 r9 $end
$scope module G1 $end
$var wire 1 ' A $end
$var wire 1 1 B $end
$var wire 1 2 C $end
$var wire 1 & Y $end
$var wire 1 9 notA $end
$var wire 1 : notB $end
$var wire 1 ; notC $end
$var wire 1 < w1 $end
$var wire 1 = w2 $end
$var wire 1 > w3 $end
$upscope $end
$scope module G2 $end
$var wire 1 3 A $end
$var wire 1 4 B $end
$var wire 1 5 C $end
$var wire 1 % Y $end
$var wire 1 ? notA $end
$var wire 1 @ notB $end
$var wire 1 A notC $end
$var wire 1 B w1 $end
$var wire 1 C w2 $end
$var wire 1 D w3 $end
$var wire 1 E w4 $end
$var wire 1 F w5 $end
$upscope $end
$scope module G3 $end
$var wire 1 6 A $end
$var wire 1 7 B $end
$var wire 1 8 C $end
$var wire 1 $ Y $end
$var wire 1 G notA $end
$var wire 1 H notB $end
$var wire 1 I notC $end
$var wire 1 J w1 $end
$var wire 1 K w2 $end
$upscope $end
$scope module OP1 $end
$var wire 1 ( A $end
$var wire 1 ) B $end
$var wire 1 * C $end
$var wire 1 # Y $end
$upscope $end
$scope module OP2 $end
$var wire 1 + A $end
$var wire 1 , B $end
$var wire 1 - C $end
$var wire 1 " Y $end
$upscope $end
$scope module OP3 $end
$var wire 1 . A $end
$var wire 1 / B $end
$var wire 1 0 C $end
$var wire 1 ! Y $end
$upscope $end
$upscope $end
$enddefinitions $end
#0
$dumpvars
xK
xJ
xI
xH
xG
xF
xE
xD
xC
xB
xA
x@
x?
0>
0=
0<
1;
1:
19
x8
x7
x6
x5
x4
x3
02
01
x0
x/
x.
x-
x,
x+
x*
x)
x(
0'
0&
x%
x$
x#
x"
x!
$end
#1
0;
12
#2
1;
0:
02
11
#3
0;
12
#4
1&
1<
1;
1:
09
02
01
1'
#5
0<
0;
1=
12
#6
0&
1;
0=
0:
02
11
#7
1&
0;
1>
12
#10
0%
1C
1D
1E
1A
1F
1@
1?
0B
05
04
03
#11
0%
0C
0A
1B
15
#12
1A
0D
0@
1C
05
14
#13
0%
0E
0A
1D
15
#14
1%
1A
1@
0?
1E
05
04
13
#15
0A
15
#16
0%
1A
0F
0@
05
14
#17
1%
0A
1F
15
#28
0$
1I
1H
1G
0J
0K
08
07
06
#29
0I
18
#30
1I
0H
08
17
#31
0I
18
#32
1$
1J
1I
1H
0G
08
07
16
#33
0I
1K
18
#34
0$
0J
1I
0K
0H
08
17
#35
1$
0I
1K
18
#37
0#
0*
0)
0(
#38
1*
#39
0*
1)
#40
1*
#41
1#
0*
0)
1(
#42
1*
#43
0#
0*
1)
#44
1#
1*
#46
0"
0-
0,
0+
#47
1-
#48
0-
1,
#49
1-
#50
1"
0-
0,
1+
#51
1-
#52
0"
0-
1,
#53
1"
1-
#55
0!
00
0/
0.
#56
10
#57
00
1/
#58
10
#59
1!
00
0/
1.
#60
10
#61
0!
00
1/
#62
1!
10
