ejercicio4/ejercicio4.v
// GATE LEVEL MODEL EJECICIO 1

// Y = (A' * C') + (A * B') + (A * C)

module gateLevel1(input wire A, B, C, output wire Y);

  wire notA, notC, notB, w1, w2, w3;

  not (notA, A);
  not (notB, B);
  not (notC, C);
  and (w1, notA, notC);
  and  (w2, A, notB);
  and (w3, A, C);
  or  (Y, w1, w2, w3);

endmodule

// Y = (B')

module gateLevel2(input wire A, B, C, output wire Y);

  not (Y, B);

endmodule

// Ecuación tabla 3, ejercicio 1

module gateLevel3(input wire A, B, C, D, output wire Y);

  wire notA, notC, notB, w1, w2, w3;

  not (notA, A);
  not (notB, B);
  not (notC, C);
  not (notD, D);
  and (w1, notA, notB, notC, notD);
  and  (w2, notA, notB, C, D);
  and (w3, notA, B, notC, D);
  and (w4, notA, B, C, notD);
  and (w5, A, notB, notC, D);
  and (w6, A, notB, C, notD);
  and (w7, A, B, notC, notD);
  and (w8, A, B, C, D);
  or  (Y, w1, w2, w3, w4, w5, w6, w7, w8);

endmodule

// Y = (A * D') + (B * D) + (A * C)

module gateLevel4(input wire A, B, C, D, output wire Y);

  wire notD, w1, w2, w3;

  not (notD, D);
  and (w1, A, notD);
  and  (w2, B, D);
  and (w3, A, C);
  or  (Y, w1, w2, w3);

endmodule


// BEHAVIORAL MODELING EJERCICIO 2

// Y = (B' * C' * D') + (A * C') + (A * D') + (A * B')

module operadores1(input wire A, B, C, D, output wire Y);

  assign Y = (~B & ~C & ~D) | (A & ~C) | (A & ~D) | (A & ~B);

endmodule

// Y = (B' + C)

module operadores2(input wire A, B, C, output wire Y);

  assign Y = (~B  | C);

endmodule

// Y = B + (C' * D) + (A * D)

module operadores3(input wire A, B, C, D, output wire Y);

  assign Y = B | (~C & D) | (A & D);

endmodule

// Y = B + (A' * C')

module operadores4(input wire A, B, C, output wire Y);

  assign Y = B | (~A & ~C);

endmodule

ejercicio4/ejercicio4_tb.v
module testbench();

  reg r1, r2, r3, r4, r5, r6, r7, r8, r9, r10, r11, r12, r13, r14, r15, r16, r17, r18, r19, r20, r21, r22, r23, r24, r25, r26,r27, r28;
  wire out1, out2, out3, out4, out5, out6, out7, out8;

  gateLevel1   G1(r1, r2, r3, out1);
  gateLevel2   G2(r4, r5, r6, out2);
  gateLevel3   G3(r7, r8, r9, r10, out3);
  gateLevel4   G4(r11, r12, r13, r14, out4);
  operadores1 OP1(r15, r16, r17, r18, out5);
  operadores2 OP2(r19, r20, r21, out6);
  operadores3 OP3(r22, r23, r24, r25, out7);
  operadores4 OP4(r26, r27, r28, out8);

  initial begin
    $display(" ejercicio 1 - tablas");
    $display("A B C | Y");
    $display("------|---");
    $monitor("%b %b %b | %b ", r1, r2, r3, out1);
    r1 = 0; r2 = 0; r3 = 0;
    #1 r3 = 1;
    #1 r2 = 1; r3 = 0;
    #1 r3 = 1;
    #1 r1 = 1; r2 = 0; r3 = 0;
    #1 r3 = 1;
    #1 r2 = 1; r3 = 0;
    #1 r3 = 1;
  end

  initial begin
    #10
    $display("\n");
    $display("A B C | Y");
    $display("------|--");
    $monitor("%b %b %b | %b", r4, r5, r6, out2);
       r4 = 0; r5 = 0; r6 = 0;
    #1 r6 = 1;
    #1 r5 = 1; r6 = 0;
    #1 r6 = 1;
    #1 r4 = 1; r5 = 0; r6 = 0;
    #1 r6 = 1;
    #1 r5 = 1; r6 = 0;
    #1 r6 = 1;
  end

  initial begin
    #19
    $display("\n");
    $display("A B C D | Y");
    $display("--------|---");
    $monitor("%b %b %b %b | %b", r7, r8, r9, r10, out3);
    r7 = 0; r8 = 0; r9 = 0; r10 = 0;
    #1 r10 = 1;
    #1 r9 = 1; r10 = 0;
    #1 r10 = 1;
    #1 r8 = 1; r9 = 0; r10 = 0;
    #1 r10 = 1;
    #1 r9 = 1; r10 = 0;
    #1 r10 = 1;
    #1 r7 =1; r8 = 0; r9 = 0; r10 = 0;
    #1 r10 = 1;
    #1 r9 = 1; r10 = 0;
    #1 r10 = 1;
    #1 r8 = 1; r9 = 0; r10 = 0;
    #1 r10 = 1;
    #1 r9 = 1; r10 = 0;
    #1 r10 = 1;
  end

  initial begin
    #36
    $display("\n");
    $display("A B C D | Y");
    $display("--------|---");
    $monitor("%b %b %b %b | %b", r11, r12, r13, r14, out4);
    r11 = 0; r12 = 0; r13 = 0; r14 = 0;
    #1 r14 = 1;
    #1 r13 = 1; r14 = 0;
    #1 r14 = 1;
    #1 r12 = 1; r13 = 0; r14 = 0;
    #1 r14 = 1;
    #1 r13 = 1; r14 = 0;
    #1 r14 = 1;
    #1 r11 =1; r12 = 0; r13 = 0; r14 = 0;
    #1 r14 = 1;
    #1 r13 = 1; r14 = 0;
    #1 r14 = 1;
    #1 r12 = 1; r13 = 0; r14 = 0;
    #1 r14 = 1;
    #1 r13 = 1; r14 = 0;
    #1 r14 = 1;
  end

  initial begin
    #53
    $display("\n");
    $display(" ejercicio 2 - ecuaciones");
    $display("A B C D | Y");
    $display("--------|---");
    $monitor("%b %b %b %b | %b", r15, r16, r17, r18, out5);
    r15 = 0; r16 = 0; r17 = 0; r18 = 0;
    #1 r18 = 1;
    #1 r17 = 1; r18 = 0;
    #1 r18 = 1;
    #1 r16 = 1; r17 = 0; r18 = 0;
    #1 r18 = 1;
    #1 r17 = 1; r18 = 0;
    #1 r18 = 1;
    #1 r15 =1; r16 = 0; r17 = 0; r18 = 0;
    #1 r18 = 1;
    #1 r17 = 1; r18 = 0;
    #1 r18 = 1;
    #1 r16 = 1; r17 = 0; r18 = 0;
    #1 r18 = 1;
    #1 r17 = 1; r18 = 0;
    #1 r18 = 1;
  end

  initial begin
    #70
    $display("\n");
    $display("A B C | Y");
    $display("------|--");
    $monitor("%b %b %b | %b", r19, r20, r21, out6);
       r19 = 0; r20 = 0; r21 = 0;
    #1 r21 = 1;
    #1 r20 = 1; r21 = 0;
    #1 r21 = 1;
    #1 r19 = 1; r20 = 0; r21 = 0;
    #1 r21 = 1;
    #1 r20 = 1; r21 = 0;
    #1 r21 = 1;
  end

  initial begin
    #79
    $display("\n");
    $display("A B C D | Y");
    $display("--------|---");
    $monitor("%b %b %b %b | %b", r22, r23, r24, r25, out7);
    r22 = 0; r23 = 0; r24 = 0; r25 = 0;
    #1 r25 = 1;
    #1 r24 = 1; r25 = 0;
    #1 r25 = 1;
    #1 r23 = 1; r24 = 0; r25 = 0;
    #1 r25 = 1;
    #1 r24 = 1; r25 = 0;
    #1 r25 = 1;
    #1 r22 = 1; r23 = 0; r24 = 0; r25 = 0;
    #1 r25 = 1;
    #1 r24 = 1; r25 = 0;
    #1 r25 = 1;
    #1 r23 = 1; r24 = 0; r25 = 0;
    #1 r25 = 1;
    #1 r24 = 1; r25 = 0;
    #1 r25 = 1;
  end

  initial begin
    #96
    $display("\n");
    $display("A B C | Y");
    $display("------|--");
    $monitor("%b %b %b | %b", r26, r27, r28, out8);
       r26 = 0; r27 = 0; r28 = 0;
    #1 r28 = 1;
    #1 r27 = 1; r28 = 0;
    #1 r28 = 1;
    #1 r26 = 1; r27 = 0; r28 = 0;
    #1 r28 = 1;
    #1 r27 = 1; r28 = 0;
    #1 r28 = 1;
  end

  initial
    #111 $finish;

  initial begin
    $dumpfile("ejercicio4_tb.vcd");
    $dumpvars(0, testbench);
  end

endmodule

ejercicio4/ejercicio4_tb.vcd
$date
	Sun Aug 09 00:15:14 2020
$end
$version
	Icarus Verilog
$end
$timescale
	1ps
$end
$scope module testbench $end
$var wire 1 ! out8 $end
$var wire 1 " out7 $end
$var wire 1 # out6 $end
$var wire 1 $ out5 $end
$var wire 1 % out4 $end
$var wire 1 & out3 $end
$var wire 1 ' out2 $end
$var wire 1 ( out1 $end
$var reg 1 ) r1 $end
$var reg 1 * r10 $end
$var reg 1 + r11 $end
$var reg 1 , r12 $end
$var reg 1 - r13 $end
$var reg 1 . r14 $end
$var reg 1 / r15 $end
$var reg 1 0 r16 $end
$var reg 1 1 r17 $end
$var reg 1 2 r18 $end
$var reg 1 3 r19 $end
$var reg 1 4 r2 $end
$var reg 1 5 r20 $end
$var reg 1 6 r21 $end
$var reg 1 7 r22 $end
$var reg 1 8 r23 $end
$var reg 1 9 r24 $end
$var reg 1 : r25 $end
$var reg 1 ; r26 $end
$var reg 1 < r27 $end
$var reg 1 = r28 $end
$var reg 1 > r3 $end
$var reg 1 ? r4 $end
$var reg 1 @ r5 $end
$var reg 1 A r6 $end
$var reg 1 B r7 $end
$var reg 1 C r8 $end
$var reg 1 D r9 $end
$scope module G1 $end
$var wire 1 ) A $end
$var wire 1 4 B $end
$var wire 1 > C $end
$var wire 1 ( Y $end
$var wire 1 E notA $end
$var wire 1 F notB $end
$var wire 1 G notC $end
$var wire 1 H w1 $end
$var wire 1 I w2 $end
$var wire 1 J w3 $end
$upscope $end
$scope module G2 $end
$var wire 1 ? A $end
$var wire 1 @ B $end
$var wire 1 A C $end
$var wire 1 ' Y $end
$upscope $end
$scope module G3 $end
$var wire 1 B A $end
$var wire 1 C B $end
$var wire 1 D C $end
$var wire 1 * D $end
$var wire 1 & Y $end
$var wire 1 K notA $end
$var wire 1 L notB $end
$var wire 1 M notC $end
$var wire 1 N notD $end
$var wire 1 O w1 $end
$var wire 1 P w2 $end
$var wire 1 Q w3 $end
$var wire 1 R w4 $end
$var wire 1 S w5 $end
$var wire 1 T w6 $end
$var wire 1 U w7 $end
$var wire 1 V w8 $end
$upscope $end
$scope module G4 $end
$var wire 1 + A $end
$var wire 1 , B $end
$var wire 1 - C $end
$var wire 1 . D $end
$var wire 1 % Y $end
$var wire 1 W notD $end
$var wire 1 X w1 $end
$var wire 1 Y w2 $end
$var wire 1 Z w3 $end
$upscope $end
$scope module OP1 $end
$var wire 1 / A $end
$var wire 1 0 B $end
$var wire 1 1 C $end
$var wire 1 2 D $end
$var wire 1 $ Y $end
$upscope $end
$scope module OP2 $end
$var wire 1 3 A $end
$var wire 1 5 B $end
$var wire 1 6 C $end
$var wire 1 # Y $end
$upscope $end
$scope module OP3 $end
$var wire 1 7 A $end
$var wire 1 8 B $end
$var wire 1 9 C $end
$var wire 1 : D $end
$var wire 1 " Y $end
$upscope $end
$scope module OP4 $end
$var wire 1 ; A $end
$var wire 1 < B $end
$var wire 1 = C $end
$var wire 1 ! Y $end
$upscope $end
$upscope $end
$enddefinitions $end
#0
$dumpvars
xZ
xY
xX
xW
xV
xU
xT
xS
xR
xQ
xP
xO
xN
xM
xL
xK
0J
0I
1H
1G
1F
1E
xD
xC
xB
xA
x@
x?
0>
x=
x<
x;
x:
x9
x8
x7
x6
x5
04
x3
x2
x1
x0
x/
x.
x-
x,
x+
x*
0)
1(
x'
x&
x%
x$
x#
x"
x!
$end
#1
0(
0H
0G
1>
#2
1(
1H
1G
0F
0>
14
#3
0(
0H
0G
1>
#4
1(
1I
1G
1F
0E
0>
04
1)
#5
0G
1J
1>
#6
0(
0I
1G
0J
0F
0>
14
#7
1(
0G
1J
1>
#10
1'
0A
0@
0?
#11
1A
#12
0'
0A
1@
#13
1A
#14
1'
0A
0@
1?
#15
1A
#16
0'
0A
1@
#17
1A
#19
1&
1O
1N
1M
0P
1L
0Q
0R
1K
0S
0T
0U
0V
0*
0D
0C
0B
#20
0&
0O
0N
1*
#21
1N
0M
0*
1D
#22
1&
0N
1P
1*
#23
0&
1N
1M
0P
0L
0*
0D
1C
#24
1&
0N
1Q
1*
#25
1&
1R
1N
0Q
0M
0*
1D
#26
0&
0R
0N
1*
#27
1N
1M
1L
0K
0*
0D
0C
1B
#28
1&
0N
1S
1*
#29
1&
1T
1N
0S
0M
0*
1D
#30
0&
0T
0N
1*
#31
1&
1U
1N
1M
0L
0*
0D
1C
#32
0&
0U
0N
1*
#33
1N
0M
0*
1D
#34
1&
0N
1V
1*
#36
0%
1W
0Y
0X
0Z
0.
0-
0,
0+
#37
0W
1.
#38
1W
0.
1-
#39
0W
1.
#40
1W
0.
0-
1,
#41
1%
0W
1Y
1.
#42
0%
1W
0Y
0.
1-
#43
1%
0W
1Y
1.
#44
1X
1%
1W
0Y
0.
0-
0,
1+
#45
0%
0X
0W
1.
#46
1X
1%
1W
1Z
0.
1-
#47
0X
0W
1.
#48
1X
1%
1W
0Z
0.
0-
1,
#49
0X
0W
1Y
1.
#50
1X
1W
0Y
1Z
0.
1-
#51
0X
0W
1Y
1.
#53
1$
02
01
00
0/
#54
0$
12
#55
02
11
#56
12
#57
02
01
10
#58
12
#59
02
11
#60
12
#61
1$
02
01
00
1/
#62
12
#63
02
11
#64
12
#65
1$
02
01
10
#66
12
#67
02
11
#68
0$
12
#70
1#
06
05
03
#71
16
#72
0#
06
15
#73
1#
16
#74
06
05
13
#75
16
#76
0#
06
15
#77
1#
16
#79
0"
0:
09
08
07
#80
1"
1:
#81
0"
0:
19
#82
1:
#83
1"
0:
09
18
#84
1:
#85
0:
19
#86
1:
#87
0"
0:
09
08
17
#88
1"
1:
#89
0"
0:
19
#90
1"
1:
#91
0:
09
18
#92
1:
#93
0:
19
#94
1:
#96
1!
0=
0<
0;
#97
0!
1=
#98
1!
0=
1<
#99
1=
#100
0!
0=
0<
1;
#101
1=
#102
1!
0=
1<
#103
1=
